stormwater_monitoring_datasheet_extraction/__init__.py
stormwater_monitoring_datasheet_extraction/api/__init__.py
stormwater_monitoring_datasheet_extraction/api/internal.py
stormwater_monitoring_datasheet_extraction/api/public.py
stormwater_monitoring_datasheet_extraction/cli/__init__.py
stormwater_monitoring_datasheet_extraction/cli/run_etl.py
stormwater_monitoring_datasheet_extraction/lib/__init__.py
stormwater_monitoring_datasheet_extraction/lib/constants.py
stormwater_monitoring_datasheet_extraction/lib/load_datasheets.py
stormwater_monitoring_datasheet_extraction/lib/db/__init__.py
stormwater_monitoring_datasheet_extraction/lib/db/read.py
stormwater_monitoring_datasheet_extraction/lib/db/tables.py
stormwater_monitoring_datasheet_extraction/lib/schema/__init__.py
stormwater_monitoring_datasheet_extraction/lib/schema/schema.py
stormwater_monitoring_datasheet_extraction/lib/schema/checks/__init__.py
stormwater_monitoring_datasheet_extraction/lib/schema/checks/dataframe_checks.py
stormwater_monitoring_datasheet_extraction/lib/schema/checks/field_checks.py
stormwater_monitoring_datasheet_extraction/lib/schema/checks/relational.py
stormwater_monitoring_datasheet_extraction-0.0.18.dist-info/licenses/LICENSE
stormwater_monitoring_datasheet_extraction-0.0.18.dist-info/METADATA
stormwater_monitoring_datasheet_extraction-0.0.18.dist-info/WHEEL
stormwater_monitoring_datasheet_extraction-0.0.18.dist-info/entry_points.txt
stormwater_monitoring_datasheet_extraction-0.0.18.dist-info/top_level.txt
stormwater_monitoring_datasheet_extraction-0.0.18.dist-info/RECORD
