Metadata-Version: 2.4
Name: stormwater_monitoring_datasheet_extraction
Version: 0.0.18
Summary: Extracts stormwater monitoring field observations from datasheet PDFs.
Author: Kaleb Coberly
Maintainer-email: kaleb.coberly@gmail.com, kris.keillor@gmail.com
Requires-Python: >=3.12
License-File: LICENSE
Requires-Dist: click<9.0.0,>=8.2.1
Requires-Dist: comb_utils<1.0.0,>=0.1.0
Requires-Dist: pandera[extensions]<0.27.0,>=0.26.1
Requires-Dist: typeguard<5.0.0,>=4.4.4
Requires-Dist: numpy<2.4.0,>=2.0.0
Requires-Dist: pandas<2.4.0,>=2.3.0
Provides-Extra: dev
Requires-Dist: stormwater_monitoring_datasheet_extraction[build]; extra == "dev"
Requires-Dist: stormwater_monitoring_datasheet_extraction[doc]; extra == "dev"
Requires-Dist: stormwater_monitoring_datasheet_extraction[qc]; extra == "dev"
Requires-Dist: stormwater_monitoring_datasheet_extraction[test]; extra == "dev"
Provides-Extra: build
Requires-Dist: build; extra == "build"
Requires-Dist: twine; extra == "build"
Requires-Dist: wheel; extra == "build"
Provides-Extra: doc
Requires-Dist: furo>=2025.7.19; extra == "doc"
Requires-Dist: sphinx<9.0.0,>=8.2.3; extra == "doc"
Requires-Dist: sphinx-autodoc-typehints<4.0.0,>=3.2.0; extra == "doc"
Requires-Dist: sphinx-click<7.0.0,>=6.0.0; extra == "doc"
Provides-Extra: qc
Requires-Dist: bandit>=1.8.6; extra == "qc"
Requires-Dist: black>=25.1.0; extra == "qc"
Requires-Dist: flake8>=7.3.0; extra == "qc"
Requires-Dist: flake8-annotations>=3.1.1; extra == "qc"
Requires-Dist: flake8-bandit>=4.1.1; extra == "qc"
Requires-Dist: flake8-black>=0.4.0; extra == "qc"
Requires-Dist: flake8-bugbear>=24.12.12; extra == "qc"
Requires-Dist: flake8-docstrings>=1.7.0; extra == "qc"
Requires-Dist: flake8-isort>=6.1.2; extra == "qc"
Requires-Dist: isort>=6.0.1; extra == "qc"
Requires-Dist: jake>=3.0.14; extra == "qc"
Requires-Dist: pytype>=2024.10.11; extra == "qc"
Requires-Dist: stormwater_monitoring_datasheet_extraction[test]; extra == "qc"
Requires-Dist: safety>=3.6.1; extra == "qc"
Provides-Extra: test
Requires-Dist: coverage[toml]>=7.9.2; extra == "test"
Requires-Dist: pydantic-core>=2.41.5; extra == "test"
Requires-Dist: pytest>=8.4.1; extra == "test"
Requires-Dist: pytest-cov>=6.2.1; extra == "test"
Dynamic: license-file
